pyspectrum/__init__.py
pyspectrum/pyspectrum.py
pyspectrum/recipes.csv
pyspectrum_MTJ-1.1.14.dist-info/LICENSE.txt
pyspectrum_MTJ-1.1.14.dist-info/METADATA
pyspectrum_MTJ-1.1.14.dist-info/WHEEL
pyspectrum_MTJ-1.1.14.dist-info/top_level.txt
pyspectrum_MTJ-1.1.14.dist-info/RECORD
